Metadata-Version: 1.0
Name: probabilityLK
Version: 0.1
Summary: Gaussian distributions
Home-page: UNKNOWN
Author: Lakshya Kwatra
Author-email: lkwatra2@gmail.com
License: UNKNOWN
Platform: UNKNOWN
